migra_idempotent/__init__.py
migra_idempotent/changes.py
migra_idempotent/command.py
migra_idempotent/migra_idempotent.py
migra_idempotent/statements.py
migra_idempotent/util.py
migra_idempotent-1.7.dist-info/entry_points.txt
migra_idempotent-1.7.dist-info/LICENSE
migra_idempotent-1.7.dist-info/WHEEL
migra_idempotent-1.7.dist-info/METADATA
migra_idempotent-1.7.dist-info/RECORD
