Metadata-Version: 2.1
Name: migra-idempotent
Version: 1.7
Summary: Like `diff` but for PostgreSQL schemas
Home-page: https://migra.djrobstep.com/
License: Unlicense
Author: Andrew Huang
Author-email: k.andrew.huang@gmail.com
Classifier: License :: Other/Proprietary License
Classifier: Programming Language :: Python :: 2
Classifier: Programming Language :: Python :: 2.7
Classifier: Programming Language :: Python :: 3
Classifier: Programming Language :: Python :: 3.4
Classifier: Programming Language :: Python :: 3.5
Classifier: Programming Language :: Python :: 3.6
Classifier: Programming Language :: Python :: 3.7
Classifier: Programming Language :: Python :: 3.8
Classifier: Programming Language :: Python :: 3.9
Provides-Extra: pg
Requires-Dist: psycopg2-binary; extra == "pg"
Requires-Dist: schemainspect_idempotent (>=0.6)
Requires-Dist: six
Requires-Dist: sqlbag
Project-URL: Repository, https://github.com/kahuang/migra
